{
  "layerVis": {
    "street": true,
    "highway": true,
    "stripe": true,
    "edgeline": true,
    "bikelane": true,
    "lot": true,
    "curb": true,
    "sidewalk": true,
    "treelawn": true,
    "building": true,
    "parking_lot": true,
    "garden": true,
    "playground": true,
    "swimming_pool": true,
    "pitch": true,
    "sports_centre": false,
    "wood": true,
    "scrub": true,
    "tree_row": true,
    "alley": true,
    "footway": true,
    "cycleway": true,
    "steps": true,
    "path": true,
    "park": true,
    "water": true,
    "tree": true,
    "lamp": true,
    "fence": true,
    "wall": true,
    "retaining_wall": true,
    "hedge": true,
    "labels": true,
    "centerline": false
  },
  "layerColors": {
    "street": "#4A4A48",
    "highway": "#2D2D2C",
    "stripe": "#F2CE4A",
    "edgeline": "#E8E4DE",
    "bikelane": "#5EA070",
    "lot": "#6a3e64",
    "curb": "#A8826A",
    "sidewalk": "#B8B2A4",
    "treelawn": "#5E8A3A",
    "building": "#3A3A3A",
    "garden": "#7EB04A",
    "playground": "#D89A4E",
    "swimming_pool": "#4A7EB0",
    "pitch": "#5E9E4A",
    "sports_centre": "#6EA05E",
    "wood": "#3E5E2E",
    "scrub": "#6E7A4A",
    "tree_row": "#4E7A3E",
    "alley": "#3E3E3C",
    "footway": "#9A8E78",
    "cycleway": "#6EA070",
    "steps": "#A0907E",
    "path": "#8E7E68",
    "park": "#5E8A3A",
    "water": "#4A6A8E",
    "tree": "#4E7A3E",
    "lamp": "#F2D67A",
    "fence": "#8A7E6E",
    "wall": "#9A8E7E",
    "retaining_wall": "#7A6E5E",
    "hedge": "#4E6E3E",
    "labels": "#2A2826"
  },
  "layerStrokes": {},
  "luColors": {
    "residential": "#5A8A3A",
    "commercial": "#A87D3E",
    "vacant": "#7A8A4E",
    "vacant-commercial": "#8A7E5E",
    "parking": "#6A6A62",
    "institutional": "#7E8AA8",
    "recreation": "#6EA03E",
    "industrial": "#8E7060"
  },
  "cornerRadiusScale": 0.9,
  "cornerRadiusOverrides": {},
  "cornerCornerRadiusOverrides": {},
  "curbWidth": 0.3302,
  "alleyCap": "square",
  "labels": {
    "size": 4,
    "weight": 500,
    "fill": "#ffffff",
    "halo": "#000000",
    "haloWidth": 0,
    "letterSpacing": 0.04,
    "opacity": 1,
    "case": "upper",
    "fontFamily": "",
    "tierScale": {
      "street": 1,
      "park": 2.8
    },
    "targetPx": 24,
    "minPx": 8,
    "maxPx": 128,
    "font": "",
    "bg": "#3a3a38",
    "bgAlpha": 1
  },
  "blockCustoms": {
    "0": {
      "5": {
        "left": {
          "pavementHW": 18.77094972067039,
          "treelawn": 3.0818657342657296,
          "sidewalk": 8.445722399109272,
          "terminal": "sidewalk"
        }
      }
    },
    "5": {
      "0": {
        "left": {
          "pavementHW": 5.258160735370765,
          "treelawn": 3.0818657342657296,
          "sidewalk": 3.5622841499694218,
          "terminal": "sidewalk"
        }
      },
      "1": {
        "left": {
          "pavementHW": 4.258903631284923,
          "treelawn": 3.0818657342657296,
          "sidewalk": 4.664848690793168,
          "terminal": "sidewalk"
        }
      },
      "2": {
        "left": {
          "pavementHW": 5.770602101268835,
          "treelawn": 3.2613357906667204,
          "sidewalk": 3.8766475078163154,
          "terminal": "sidewalk"
        }
      },
      "3": {
        "left": {
          "pavementHW": 4.258903631284923,
          "treelawn": 3.0818657342657296,
          "sidewalk": 3.6372151821695518,
          "terminal": "sidewalk"
        }
      },
      "4": {
        "left": {
          "pavementHW": 6.826240166083942,
          "treelawn": 1.00584,
          "sidewalk": 2.4384,
          "terminal": "sidewalk"
        },
        "right": {
          "pavementHW": 6.783489947552418,
          "treelawn": 1,
          "sidewalk": 2.4384,
          "terminal": "sidewalk"
        }
      }
    },
    "5.0,79.0": {
      "4": {
        "pavementHW": 17.434450046086596,
        "treelawn": 3.0818657342657296,
        "sidewalk": 8.445722399109272,
        "terminal": "sidewalk"
      }
    },
    "-0.5,10.0": {
      "0": {
        "pavementHW": 5,
        "treelawn": 1.5,
        "sidewalk": 3.4500753030844287,
        "terminal": "sidewalk"
      },
      "1": {
        "pavementHW": 14.204480582332497,
        "treelawn": 3.0818657342657296,
        "sidewalk": 4.018471708949441,
        "terminal": "sidewalk"
      },
      "2": {
        "pavementHW": 16.056810998735838,
        "treelawn": 1.5,
        "sidewalk": 1.5,
        "terminal": "sidewalk"
      }
    },
    "-82.5,0.0": {
      "3": {
        "pavementHW": 1.9721871049304625,
        "treelawn": 1.0668,
        "sidewalk": 4.696599578204427,
        "terminal": "sidewalk"
      }
    },
    "-0.5,-80.0": {
      "1": {
        "pavementHW": 10.939934788692518,
        "treelawn": 3.0818657342657296,
        "sidewalk": 1.6913619949919116,
        "terminal": "sidewalk"
      }
    },
    "-82.5,-80.0": {
      "3": {
        "pavementHW": 20.287220164694233,
        "treelawn": 1,
        "sidewalk": 4.696599578204427,
        "terminal": "sidewalk"
      }
    },
    "-82.5,80.0": {
      "3": {
        "pavementHW": 1.7378727120418702,
        "treelawn": 1,
        "sidewalk": 4.696599578204427,
        "terminal": "sidewalk"
      }
    },
    "80.0,-80.0": {
      "1": {
        "pavementHW": 10.864214601769895,
        "treelawn": 1.5,
        "sidewalk": 1.5,
        "terminal": "sidewalk"
      }
    },
    "-78.5,80.0": {
      "3": {
        "pavementHW": 6.2484,
        "treelawn": 11.263722578889858,
        "sidewalk": 9.279459719103926,
        "terminal": "sidewalk"
      }
    },
    "11.5,79.0": {
      "4": {
        "pavementHW": 6.2484,
        "treelawn": 3.0818657342657296,
        "sidewalk": 4.7244,
        "terminal": "sidewalk"
      }
    }
  },
  "blockLandUse": {},
  "materialColors": {},
  "materialPhysics": {},
  "buildingPalette": [
    "#dcdcdc",
    "#a0522d",
    "#cd853f",
    "#8b2500",
    "#d2b48c",
    "#778899",
    "#8b4513",
    "#a52a2a",
    "#f5deb3",
    "#696969",
    "#b22222",
    "#808080"
  ],
  "lampGlow": {
    "animated": "tod",
    "transitionIn": 30,
    "transitionOut": 30,
    "values": {
      "sunset": {
        "grass": 0.5,
        "trees": 0.005,
        "pool": 0.1
      },
      "night": {
        "grass": 0.5,
        "trees": 0.06,
        "pool": 0.25
      }
    }
  },
  "bloom": {
    "values": {
      "intensity": 0.5,
      "threshold": 0.85,
      "smoothing": 0.4
    }
  },
  "warmth": {
    "values": {
      "value": 0
    }
  },
  "fill": {
    "values": {
      "value": 0.65
    }
  },
  "exposure": {
    "values": {
      "value": 0.95
    }
  },
  "ao": {
    "values": {
      "radius": 15,
      "intensity": 2.5,
      "distanceFalloff": 0.3
    }
  },
  "mist": {
    "values": {
      "density": 0,
      "color": "#9dc5e0"
    }
  },
  "halo": {
    "values": {
      "strength": 0,
      "color": "#b8c8d8"
    }
  },
  "grade": {
    "values": {
      "contrast": 0.42,
      "toe": 0.28,
      "saturation": 1.1,
      "vignette": 1
    }
  },
  "grain": {
    "values": {
      "scale": 1
    }
  },
  "shadow": {
    "values": {
      "size": 52,
      "samples": 16
    }
  },
  "constellations": {
    "values": {
      "value": 0
    }
  },
  "milkyWay": {
    "values": {
      "value": 1
    }
  },
  "neon": {
    "values": {
      "core": 1,
      "tube": 1,
      "bleed": 1
    }
  },
  "neonTube": {
    "values": {
      "tubeRadius": 0.2,
      "roofLift": 0.3,
      "emissive": 4
    }
  },
  "sky": {
    "values": {
      "dawn": [
        {
          "horizon": "#3a2838",
          "low": "#30254a",
          "mid": "#151838",
          "high": "#0a0c1a",
          "sunGlow": "#000000"
        },
        {
          "horizon": "#4d3245",
          "low": "#4a3060",
          "mid": "#241e48",
          "high": "#10122a",
          "sunGlow": "#220c08"
        },
        {
          "horizon": "#7a5048",
          "low": "#603e62",
          "mid": "#34286e",
          "high": "#0e1230",
          "sunGlow": "#7a2818"
        },
        {
          "horizon": "#c07050",
          "low": "#885578",
          "mid": "#4a3878",
          "high": "#141838",
          "sunGlow": "#dd4433"
        }
      ],
      "sunrise": [
        {
          "horizon": "#dda065",
          "low": "#b08088",
          "mid": "#7068b0",
          "high": "#223060",
          "sunGlow": "#ee7755"
        },
        {
          "horizon": "#d8aa6f",
          "low": "#aa8898",
          "mid": "#7480b8",
          "high": "#2c4080",
          "sunGlow": "#ffaa66"
        },
        {
          "horizon": "#d0b888",
          "low": "#a8a0a8",
          "mid": "#7895c0",
          "high": "#3a6aaa",
          "sunGlow": "#ffbb77"
        },
        {
          "horizon": "#b8c5b8",
          "low": "#90b0c8",
          "mid": "#6098d0",
          "high": "#4080d8",
          "sunGlow": "#ffd1a0"
        }
      ],
      "noon": [
        {
          "horizon": "#9dc5e0",
          "low": "#80b5e0",
          "mid": "#5a9ce0",
          "high": "#4a90e0",
          "sunGlow": "#ffeedd"
        }
      ],
      "golden": [
        {
          "horizon": "#a8c0d8",
          "low": "#88b0d8",
          "mid": "#609bd8",
          "high": "#4888d8",
          "sunGlow": "#ffe0bb"
        },
        {
          "horizon": "#bcb5a8",
          "low": "#9aa0b0",
          "mid": "#7095bf",
          "high": "#3c70b2",
          "sunGlow": "#ffcc88"
        },
        {
          "horizon": "#ccaa70",
          "low": "#aa9088",
          "mid": "#7090bb",
          "high": "#3a68a8",
          "sunGlow": "#ffaa55"
        },
        {
          "horizon": "#d09665",
          "low": "#b08077",
          "mid": "#7080b0",
          "high": "#2e588f",
          "sunGlow": "#ff9a4a"
        }
      ],
      "sunset": [
        {
          "horizon": "#dd8840",
          "low": "#bb7065",
          "mid": "#6858a0",
          "high": "#1a2555",
          "sunGlow": "#ff7733"
        },
        {
          "horizon": "#dc7438",
          "low": "#b06060",
          "mid": "#5848a0",
          "high": "#172048",
          "sunGlow": "#ff5520"
        },
        {
          "horizon": "#cc6030",
          "low": "#a05058",
          "mid": "#4a3570",
          "high": "#141835",
          "sunGlow": "#ff3318"
        },
        {
          "horizon": "#a04a2c",
          "low": "#704050",
          "mid": "#2e2655",
          "high": "#0e1228",
          "sunGlow": "#cc2812"
        }
      ],
      "dusk": [
        {
          "horizon": "#7a3828",
          "low": "#40253a",
          "mid": "#181535",
          "high": "#0a0c1a",
          "sunGlow": "#882010"
        },
        {
          "horizon": "#502a28",
          "low": "#2a1a30",
          "mid": "#10112a",
          "high": "#070914",
          "sunGlow": "#3a1008"
        },
        {
          "horizon": "#2c2028",
          "low": "#181420",
          "mid": "#0c0e1a",
          "high": "#06070e",
          "sunGlow": "#100404"
        },
        {
          "horizon": "#1a1525",
          "low": "#0f0f18",
          "mid": "#080810",
          "high": "#050508",
          "sunGlow": "#000000"
        }
      ],
      "night": [
        {
          "horizon": "#1a1525",
          "low": "#0f0f18",
          "mid": "#080810",
          "high": "#050508",
          "sunGlow": "#000000"
        }
      ]
    }
  },
  "ambient": {
    "values": {
      "value": 1.58
    }
  },
  "hemi": {
    "values": {
      "value": 1
    }
  },
  "dirSun": {
    "values": {
      "value": 1
    }
  },
  "dirMoon": {
    "values": {
      "value": 1
    }
  },
  "heroSubject": null,
  "heroKeyframes": [
    {
      "position": [
        -540,
        55,
        362
      ],
      "fov": 22
    },
    {
      "position": [
        -260,
        55,
        98
      ],
      "fov": 22
    }
  ],
  "heroMotion": {
    "period": 720,
    "easing": "sine"
  },
  "shots": {
    "values": {
      "browse": {
        "fov": 45,
        "padding": 1.05,
        "bounds": {
          "cx": 95,
          "cz": -158,
          "w": 1292,
          "h": 1025
        }
      },
      "hero": {
        "fov": 22
      },
      "street": {
        "fov": 75,
        "eyeHeight": 1.73
      }
    }
  },
  "browseHeading": {
    "values": {
      "value": 0
    }
  },
  "arch": {
    "values": {
      "distance": 1050,
      "bearingX": 0.9487,
      "bearingZ": -0.3163,
      "scale": 1.3,
      "rotation": 1.36,
      "yOffset": 0,
      "footFade": 30,
      "uplightL_intensity": 0,
      "uplightL_color": "#ffd6a8",
      "uplightL_cone": 0.55,
      "uplightL_reach": 200,
      "uplightR_intensity": 0,
      "uplightR_color": "#ffd6a8",
      "uplightR_cone": 0.55,
      "uplightR_reach": 200
    }
  },
  "horizon": {
    "values": {
      "radius": 3750,
      "fadeInner": 900,
      "fadeOuter": 3750
    }
  },
  "clouds": {
    "values": {
      "preset": "auto",
      "overrides": null
    }
  },
  "openSections": {
    "Streets": true,
    "Blocks": true,
    "Paths": false,
    "Features": false,
    "Labels": false,
    "HeroSubject": false,
    "Look": false,
    "Land Cover": false
  },
  "trees": [
    {
      "species": "cedar_generic",
      "variantId": 1
    },
    {
      "species": "broadleaf_rt3",
      "variantId": 1
    },
    {
      "species": "alaskan_cedar_2",
      "variantId": 1
    },
    {
      "species": "platanus_acerifolia",
      "variantId": 6
    },
    {
      "species": "platanus_acerifolia",
      "variantId": 7
    },
    {
      "species": "platanus_acerifolia",
      "variantId": 8
    },
    {
      "species": "platanus_acerifolia",
      "variantId": 9
    },
    {
      "species": "platanus_acerifolia",
      "variantId": 10
    },
    {
      "species": "generic_leaf_tree",
      "variantId": 3
    },
    {
      "species": "generic_tree_2",
      "variantId": 1
    },
    {
      "species": "platanus_acerifolia",
      "variantId": 4
    },
    {
      "species": "platanus_acerifolia",
      "variantId": 3
    },
    {
      "species": "platanus_acerifolia",
      "variantId": 2
    },
    {
      "species": "platanus_acerifolia",
      "variantId": 1
    }
  ]
}